{
  "_fv": 39,
  "_type": "recipe",
  "definition": {
    "recipeType": "Crafting",
    "xpReward": 0.0,
    "cookingTime": 200,
    "recipeRetstackSize": 1,
    "group": "",
    "recipeShapeless": true,
    "recipeSlots": [
      {
        "value": "CUSTOM:CaperLeaves"
      },
      {
        "value": "CUSTOM:MortarPestle"
      },
      {
        "value": ""
      },
      {
        "value": "Items.GLASS_BOTTLE"
      },
      {
        "value": ""
      },
      {
        "value": ""
      },
      {
        "value": ""
      },
      {
        "value": ""
      },
      {
        "value": ""
      }
    ],
    "recipeReturnStack": {
      "value": "CUSTOM:Rennet"
    },
    "name": "rennet_recipe",
    "namespace": "mod"
  }
}